py_own_lang_dect_pkg/__init__.py
py_own_lang_dect_pkg/config.py
py_own_lang_dect_pkg-0.1.2.dist-info/LICENSE
py_own_lang_dect_pkg-0.1.2.dist-info/METADATA
py_own_lang_dect_pkg-0.1.2.dist-info/WHEEL
py_own_lang_dect_pkg-0.1.2.dist-info/top_level.txt
py_own_lang_dect_pkg-0.1.2.dist-info/RECORD
